Metadata-Version: 1.2
Name: cryptonight
Version: 0.1
Summary: Fast CPU-based cryptonight hashing library
Home-page: https://www.mcdonalds.com.au
Author: Michael Gauthier
Author-email: mgauthier5@protonmail.ch
License: UNKNOWN
Project-URL: Funding, https://donate.pypi.org
Project-URL: Bug Reports, https://github.com/pypa/sampleproject/issues
Project-URL: Say Thanks!, http://saythanks.io/to/example
Project-URL: Source, https://github.com/pypa/sampleproject/
Keywords: cryptonight hashing cryptography
Platform: UNKNOWN
Classifier: Development Status :: 3 - Alpha
Classifier: Intended Audience :: Developers
Classifier: Topic :: Software Development :: Build Tools
Classifier: License :: OSI Approved :: MIT License
Classifier: Programming Language :: Python :: 2
Classifier: Programming Language :: Python :: 2.7
Classifier: Programming Language :: Python :: 3
Classifier: Programming Language :: Python :: 3.4
Classifier: Programming Language :: Python :: 3.5
Classifier: Programming Language :: Python :: 3.6
